README.md
dist-requirements.txt
xtremcache/__init__.py
xtremcache/__main__.py
xtremcache/archivermanager.py
xtremcache/bddmanager.py
xtremcache/cachemanager.py
xtremcache/configuration.py
xtremcache/exceptions.py
xtremcache/main.py
xtremcache/utils.py
xtremcache/version.py
xtremcache/ext/msys2/unzip/v6.00/bin/msys-2.0.dll
xtremcache/ext/msys2/unzip/v6.00/bin/msys-bz2-1.dll
xtremcache/ext/msys2/unzip/v6.00/bin/unzip.exe
xtremcache/ext/msys2/zip/v3.0/bin/msys-2.0.dll
xtremcache/ext/msys2/zip/v3.0/bin/msys-bz2-1.dll
xtremcache/ext/msys2/zip/v3.0/bin/zip.exe
xtremcache-2.2.1.dist-info/LICENSE
xtremcache-2.2.1.dist-info/METADATA
xtremcache-2.2.1.dist-info/WHEEL
xtremcache-2.2.1.dist-info/entry_points.txt
xtremcache-2.2.1.dist-info/top_level.txt
xtremcache-2.2.1.dist-info/RECORD
