Metadata-Version: 2.1
Name: xtremcache
Version: 2.2.1
Summary: Handle generic file and directories caching
Author: xtrembuffalo
Author-email: tristan.cladet@gmail.com
License: GPL-3.0
Project-URL: Documentation, https://github.com/xtrembuffalo/xtremcache/blob/main/README.md
Project-URL: Source, https://github.com/xtrembuffalo/xtremcache
Project-URL: Tracker, https://github.com/xtrembuffalo/xtremcache/issues
Keywords: cache caching store storage file files folder folders archive archives rep repertory repertories
Classifier: Development Status :: 5 - Production/Stable
Classifier: Environment :: Console
Classifier: Environment :: Plugins
Classifier: Intended Audience :: Developers
Classifier: Intended Audience :: System Administrators
Classifier: License :: OSI Approved :: GNU General Public License v3 (GPLv3)
Classifier: Natural Language :: English
Classifier: Operating System :: Microsoft :: Windows
Classifier: Operating System :: Unix
Classifier: Programming Language :: Python :: 3
Classifier: Programming Language :: Python :: 3 :: Only
Classifier: Topic :: Software Development
Classifier: Topic :: System :: Archiving
Classifier: Typing :: Typed
Requires-Python: >=3.8
License-File: LICENSE
Requires-Dist: build
Requires-Dist: twine
Requires-Dist: PyYAML (<7.0,>=6.0)
Requires-Dist: SQLAlchemy (<2.0.0,>=1.4.35)
Requires-Dist: tabulate (>=0.9.0<1.0.0)
